pandora2d/Pandora2d.py
pandora2d/__init__.py
pandora2d/check_configuration.py
pandora2d/common.py
pandora2d/constants.py
pandora2d/criteria.py
pandora2d/img_tools.py
pandora2d/margins.py
pandora2d/memory_estimation.py
pandora2d/profiling.py
pandora2d/reporting.py
pandora2d/schema.py
pandora2d/state_machine.py
pandora2d/statistics.py
pandora2d/common_cpp/__init__.py
pandora2d/common_cpp/common_bind.cpython-313-x86_64-linux-gnu.so
pandora2d/common_cpp/common_bind.pyi
pandora2d/common_cpp/meson.build
pandora2d/common_cpp/include/constant.hpp
pandora2d/common_cpp/include/cost_volume.hpp
pandora2d/common_cpp/include/margins.hpp
pandora2d/common_cpp/include/operation.hpp
pandora2d/common_cpp/include/pandora2d_type.hpp
pandora2d/common_cpp/src/bind.cpp
pandora2d/common_cpp/src/operation.cpp
pandora2d/cost_volume_confidence/__init__.py
pandora2d/cost_volume_confidence/ambiguity.py
pandora2d/cost_volume_confidence/cost_volume_confidence.py
pandora2d/cost_volume_confidence/registry.py
pandora2d/disparity/__init__.py
pandora2d/disparity/disparity.py
pandora2d/estimation/__init__.py
pandora2d/estimation/estimation.py
pandora2d/estimation/phase_cross_correlation.py
pandora2d/interpolation_filter/__init__.py
pandora2d/interpolation_filter/bicubic.py
pandora2d/interpolation_filter/bicubic_cpp.py
pandora2d/interpolation_filter/cardinal_sine.py
pandora2d/interpolation_filter/cardinal_sine_cpp.py
pandora2d/interpolation_filter/interpolation_filter.py
pandora2d/interpolation_filter_cpp/__init__.py
pandora2d/interpolation_filter_cpp/interpolation_filter_bind.cpython-313-x86_64-linux-gnu.so
pandora2d/interpolation_filter_cpp/interpolation_filter_bind.pyi
pandora2d/interpolation_filter_cpp/meson.build
pandora2d/interpolation_filter_cpp/include/bicubic.hpp
pandora2d/interpolation_filter_cpp/include/cardinal_sine.hpp
pandora2d/interpolation_filter_cpp/include/interpolation_filter.hpp
pandora2d/interpolation_filter_cpp/src/bicubic.cpp
pandora2d-1.0.0.dist-info/METADATA
pandora2d-1.0.0.dist-info/WHEEL
pandora2d-1.0.0.dist-info/entry_points.txt
pandora2d-1.0.0.dist-info/RECORD
