Metadata-Version: 2.1
Name: pandora2d
Version: 1.0.0
Summary: A coregistration tool.
Author: CNES
Classifier: Development Status :: 4 - Beta
Classifier: Environment :: Console
Classifier: Intended Audience :: Developers
Classifier: Intended Audience :: End Users/Desktop
Classifier: Intended Audience :: Science/Research
Classifier: License :: OSI Approved :: Apache Software License
Classifier: Operating System :: OS Independent
Classifier: Programming Language :: Python
Classifier: Programming Language :: Python :: 3
Classifier: Programming Language :: Python :: 3 :: Only
Classifier: Programming Language :: Python :: 3.9
Classifier: Programming Language :: Python :: 3.10
Classifier: Programming Language :: Python :: 3.11
Classifier: Programming Language :: Python :: 3.12
Classifier: Programming Language :: Python :: 3.13
Classifier: Topic :: Software Development :: Libraries :: Python Modules
Classifier: Typing :: Typed
Project-URL: Homepage, https://pandora2d.readthedocs.io
Project-URL: Documentation, https://pandora2d.readthedocs.io/en/latest/
Project-URL: Repository, https://github.com/CNES/Pandora2D
Project-URL: Issues, https://github.com/CNES/Pandora2D/issues
Project-URL: Changelog, https://github.com/CNES/Pandora2D/blob/master/CHANGELOG.md
Requires-Python: >=3.9
Requires-Dist: json-checker
Requires-Dist: matplotlib
Requires-Dist: numpy
Requires-Dist: pandas
Requires-Dist: pandora>=1.6.4
Requires-Dist: psutil
Requires-Dist: rasterio
Requires-Dist: scikit-image
Requires-Dist: scipy
Requires-Dist: transitions
Requires-Dist: typing_extensions
Requires-Dist: xarray
Provides-Extra: dev
Requires-Dist: pandora2d[test]; extra == "dev"
Requires-Dist: black>=21.5b0; extra == "dev"
Requires-Dist: cppcheck; extra == "dev"
Requires-Dist: isort>=5.8.0; extra == "dev"
Requires-Dist: mypy; extra == "dev"
Requires-Dist: pandas-stubs; extra == "dev"
Requires-Dist: pre-commit; extra == "dev"
Requires-Dist: pylint>=3.3.6; extra == "dev"
Requires-Dist: setuptools_scm; extra == "dev"
Requires-Dist: types-psutil; extra == "dev"
Provides-Extra: test
Requires-Dist: pytest; extra == "test"
Requires-Dist: pytest-cov; extra == "test"
Requires-Dist: pytest-html; extra == "test"
Requires-Dist: pytest-mock; extra == "test"
Requires-Dist: pytest-monitor; extra == "test"
Requires-Dist: gcovr; extra == "test"
Provides-Extra: docs
Requires-Dist: sphinx; extra == "docs"
Requires-Dist: sphinx_autoapi; extra == "docs"
Requires-Dist: sphinx_rtd_theme; extra == "docs"
Requires-Dist: sphinx_tabs; extra == "docs"
Provides-Extra: notebook
Requires-Dist: graphviz; extra == "notebook"
Requires-Dist: notebook; extra == "notebook"
Provides-Extra: mccnn
Requires-Dist: pandora[mccnn]; extra == "mccnn"
